{
    "book-info": "معلومات الحجز",
    "guest-data": "بيانات الضيف",
    "special-demands": "طلبات خاصة",
    "special-demands-warning": "لا يمكن ضمان الطلبات الخاصة - لكن سنبذل قصارى جهدنا لتلبية احتياجاتك.",
    "bank-transfer": "تحويل بنكي",
    "choose-bank-we-send-details":"اختر البنك الذى يناسبك وسنرسل لك التفصيل على الايميل.",
    "reservation-state":"حالة الحجز",
    "price":"السعر",
    "arrival-date":"تاريخ الوصول",
    "departure-date": "تاريخ المغادرة",
    "booked-at":"تم الحجز في",
    "hotel":"فندق"
}